AUTHORS.TXT
CHANGELOG.rst
INSTALL.rst
LICENSE.TXT
MANIFEST.in
README.rst
THANKS.TXT
TODO.TXT
setup.cfg
setup.py
docs/_build/html/.buildinfo
docs/_build/html/decision.html
docs/_build/html/genindex.html
docs/_build/html/index.html
docs/_build/html/introduction.html
docs/_build/html/lowprev.html
docs/_build/html/objects.inv
docs/_build/html/py-modindex.html
docs/_build/html/quickstart.html
docs/_build/html/search.html
docs/_build/html/searchindex.js
docs/_build/html/setfunction.html
docs/_build/html/_images/math/019e9892786e493964e145e7c5cf7b700314e53b.png
docs/_build/html/_images/math/0d809708839c47a746d39111cd5218fbd02e5bfe.png
docs/_build/html/_images/math/1464fc52485b53540d8260aa6e1be67f72015b15.png
docs/_build/html/_images/math/174fadd07fd54c9afe288e96558c92e0c1da733a.png
docs/_build/html/_images/math/1a7029f061cf3e9be1d6a836658f962dc3945e02.png
docs/_build/html/_images/math/2744600189f7f1df31756f2022b2d5212ef1c767.png
docs/_build/html/_images/math/2a2df1df1f79999382ee7184370e5633941fa615.png
docs/_build/html/_images/math/2d8c833ed800824727cd7bd2fb9de1a12ad7e674.png
docs/_build/html/_images/math/3469de16aca936ee19e56edc820a1cf9b054402f.png
docs/_build/html/_images/math/3e06942089226c46c87dbe43d53706d932a84815.png
docs/_build/html/_images/math/40c72d502b24768266a0dca0623acf56beb3cb75.png
docs/_build/html/_images/math/41aa4770aeb46848b0f21a0dc8155d7d643ace58.png
docs/_build/html/_images/math/4287918a1e5d80ceca739c25c5dab08f6de21e48.png
docs/_build/html/_images/math/4b4cade9ca8a2c8311fafcf040bc5b15ca507f52.png
docs/_build/html/_images/math/5272a6eca80ebd37759ae7a715af2e00aa3c45b6.png
docs/_build/html/_images/math/54d7d48553f4d9e7ab418118607ea324cbfddfda.png
docs/_build/html/_images/math/55ff9df91e57651bf3df23ecf7ab48925428ebf2.png
docs/_build/html/_images/math/565f44aa56208290108f3cc6b9dae926ca1da3a1.png
docs/_build/html/_images/math/6186a2725157d89b16e66edd34cb187e4a11751f.png
docs/_build/html/_images/math/62ac3c9e88c610d76e46fb242028a3376ca43979.png
improb.egg-info/PKG-INFO
improb.egg-info/SOURCES.txt
improb.egg-info/dependency_links.txt
improb.egg-info/top_level.txt
