Metadata-Version: 1.0
Name: improb
Version: 0.1.1
Summary: improb is a Python module for working with imprecise probabilities.
Home-page: http://pypi.python.org/pypi/improb/
Author: Matthias Troffaes
Author-email: matthias.troffaes@gmail.com
License: GPL
Keywords: statistics,lower prevision,imprecise probability,credal set
Platform: any
Classifier: Development Status :: 3 - Alpha
Classifier: License :: OSI Approved :: GNU General Public License (GPL)
Classifier: Intended Audience :: Developers
Classifier: Intended Audience :: End Users/Desktop
Classifier: Intended Audience :: Science/Research
Classifier: Topic :: Scientific/Engineering :: Mathematics
Classifier: Programming Language :: Python
Classifier: Programming Language :: Python :: 2
Classifier: Operating System :: OS Independent
